slycache/__init__.py
slycache/actions.py
slycache/const.py
slycache/exceptions.py
slycache/interface.py
slycache/invocations.py
slycache/key_generator.py
slycache/slycache.py
slycache/ext/__init__.py
slycache/ext/django/__init__.py
slycache/ext/django/apps.py
slycache/ext/flask/__init__.py
slycache-0.3.1.dist-info/METADATA
slycache-0.3.1.dist-info/WHEEL
slycache-0.3.1.dist-info/licenses/LICENSE
slycache-0.3.1.dist-info/RECORD
