Metadata-Version: 2.4
Name: slycache
Version: 0.3.1
Summary: Service caching API
Author-email: Simon Kelly <simongdkelly@gmail.com>
License-Expression: BSD-3-Clause
License-File: LICENSE
Classifier: Development Status :: 4 - Beta
Classifier: Framework :: Django
Classifier: Framework :: Flask
Classifier: Intended Audience :: Developers
Classifier: License :: OSI Approved :: BSD License
Classifier: Natural Language :: English
Classifier: Programming Language :: Python :: 3
Classifier: Programming Language :: Python :: 3.6
Classifier: Programming Language :: Python :: 3.7
Classifier: Programming Language :: Python :: 3.8
Classifier: Programming Language :: Python :: 3.9
Requires-Python: >=3.11
Provides-Extra: django
Requires-Dist: django>=5.1.4; extra == 'django'
Provides-Extra: flask
Requires-Dist: flask-caching>=2.3.0; extra == 'flask'
